{
	"details": {
		"id": "un-pacto",
		"title": "Un pacto",
		"artist": "Bersuit Vergarabat",
		"album": "De la cabeza con Bersuit Vergarabat",
		"year": 2002,
		"country": "游뷣릖",
		"category": "2|WELL_DONE|游녨",
		"created_at": "2021/10/02",
		"is_public": true,
		"in_progress": false,
		"spotify_url": "https://open.spotify.com/track/4J2Jf2GvaOSINTlTTHdmse",
		"youtube_url": "https://youtu.be/WNebXvrqGDE",
		"assets": {},
		"sources": [
			{
				"text": "Como tocar un pacto para vivir - Bersuit",
				"url": "https://youtu.be/weOrhfR4k8I",
				"source": "youtube"
			},
			{
				"text": "Como tocar UN PACTO Bersuit en Guitarra [ACORDES+RASGIDOS+ARPEGIOS] TAB f치cil!!",
				"url": "https://youtu.be/QuTv6yFfsTY",
				"source": "youtube"
			},
			{
				"text": "COMO TOCAR \"Un pacto\" de La Bersuit | Tutorial guitarra ac칰stica/criolla acordes arpegio rasgueo",
				"url": "https://youtu.be/pg7o0Y8u3Vs",
				"source": "youtube"
			},
			{
				"text": "UN PACTO PARA VIVIR, Bersuit Vergarabat: Acordes",
				"url": "https://acordes.lacuerda.net/bersuit/un_pacto_para_vivir.shtml",
				"source": "lacuerda"
			}
		],
		"chords": []
	},
	"mdx": "<TextFormatter>{DATA.song.parsedLyrics}</TextFormatter>",
	"txt": "G\nUn pacto para vivir, odi치ndonos sol a sol\n             D\nrevolviendo m치s\n           Em          C\nen los restos, de un amor\n D             C     D               Em\ncon un camino recto, a la desesperaci칩n\n Bm              B7           G\ndesenlace en un cuento de terror\n\nG G\n\nG\n6 a침os as칤, escapando a un mismo lugar\n             D\ncon mi fantas칤a\n                   Em       C\nbuscando otro cuerpo, otra voz\n D                     C    D             Em\nfui consumiendo infiernos, para salir de vos\nBm             B7          G\nintoxicado, loco y, sin humor\n\nG G\nC C C C G C G   C C C C G C G\n\n G\nSi hoy te tuviera aqu칤, cuando hago esta canci칩n,\n               D\nme sentir칤a raro\n             Em              C\nno tengo sue침o, mi panza vibra\n D                     C   D                  Em\ntuve un golpe energ칠tico, milagro y resurrecci칩n\nBm                   B7           G\ny eso que estaba tieso, bajo control\n\nG\n\nG                        G                 G\nEl poder siempre manda, si para tenerte aqu칤\n                     D\nhabr칤a que maltratarte\n               Em         C\nno puedo hacerlo, sos mi Dios\n    D                      C        D                 Em\nte veo, me sonrojo y tiemblo, que idiota te hace el amor\nBm                      B7                  C\ny hoy quiero darle rienda, a esta superstici칩n\n\nC C C C\n\nG\nUn pacto para vivir\nG\nUn pacto para vivir\nG\nUn pacto para vivir\n\nC C C C G G\n\nG\nUn pacto para vivir\nG\nUn pacto para vivir\nG\nUn pacto para vivir\n\nC C C C G G\n\nG\nUn pacto para vivir\nG\nUn pacto para vivir\nG\nUn pacto para vivir\n\nG              C G    C      G\nUn pacto para vivir, para vivir"
}
